systemdcli/__init__.py
systemdcli/init_command.py
systemdcli/main.py
systemdcli-0.1.6.dist-info/entry_points.txt
systemdcli-0.1.6.dist-info/METADATA
systemdcli-0.1.6.dist-info/WHEEL
systemdcli-0.1.6.dist-info/RECORD
